pyrockoeost/__init__.py
pyrockoeost/ahfullgreen.py
pyrockoeost/ahfullgreen_ext.cp310-win_amd64.pyd
pyrockoeost/automap.py
pyrockoeost/autopick.py
pyrockoeost/autopick_ext.cp310-win_amd64.pyd
pyrockoeost/avl.cp310-win_amd64.pyd
pyrockoeost/beachball.py
pyrockoeost/cake.py
pyrockoeost/cake_plot.py
pyrockoeost/catalog.py
pyrockoeost/color.py
pyrockoeost/config.py
pyrockoeost/crust2x2.py
pyrockoeost/crustdb.py
pyrockoeost/css.py
pyrockoeost/datacube.py
pyrockoeost/datacube_ext.cp310-win_amd64.pyd
pyrockoeost/deps.py
pyrockoeost/dummy_progressbar.py
pyrockoeost/eikonal_ext.cp310-win_amd64.pyd
pyrockoeost/evalresp.py
pyrockoeost/eventdata.py
pyrockoeost/example.py
pyrockoeost/file.py
pyrockoeost/gcf.py
pyrockoeost/geometry.py
pyrockoeost/geonames.py
pyrockoeost/get_terminal_size.py
pyrockoeost/gmtpy.py
pyrockoeost/gse1.py
pyrockoeost/gse2_io_wrap.py
pyrockoeost/gui_util.py
pyrockoeost/guts.py
pyrockoeost/guts_agnostic.py
pyrockoeost/guts_array.py
pyrockoeost/hamster_pile.py
pyrockoeost/has_paths.py
pyrockoeost/himesh.py
pyrockoeost/hudson.py
pyrockoeost/icosphere.py
pyrockoeost/ims.py
pyrockoeost/ims_ext.cp310-win_amd64.pyd
pyrockoeost/info.py
pyrockoeost/io_common.py
pyrockoeost/iris_ws.py
pyrockoeost/kan.py
pyrockoeost/marker.py
pyrockoeost/moment_tensor.py
pyrockoeost/mseed.py
pyrockoeost/mseed_ext.cp310-win_amd64.pyd
pyrockoeost/orthodrome.py
pyrockoeost/orthodrome_ext.cp310-win_amd64.pyd
pyrockoeost/parimap.py
pyrockoeost/parstack.py
pyrockoeost/parstack_ext.cp310-win_amd64.pyd
pyrockoeost/pchain.py
pyrockoeost/pile.py
pyrockoeost/pile_viewer.py
pyrockoeost/print_version.py
pyrockoeost/progress.py
pyrockoeost/pz.py
pyrockoeost/rdseed.py
pyrockoeost/response.py
pyrockoeost/response_plot.py
pyrockoeost/sacio.py
pyrockoeost/segy.py
pyrockoeost/seisan_response.py
pyrockoeost/seisan_waveform.py
pyrockoeost/shadow_pile.py
pyrockoeost/signal_ext.cp310-win_amd64.pyd
pyrockoeost/snuffler.py
pyrockoeost/snuffling.py
pyrockoeost/spit.py
pyrockoeost/suds.py
pyrockoeost/table.py
pyrockoeost-2024.21.dist-info/AUTHORS.md
pyrockoeost-2024.21.dist-info/LICENSE.md
pyrockoeost-2024.21.dist-info/METADATA
pyrockoeost-2024.21.dist-info/WHEEL
pyrockoeost-2024.21.dist-info/entry_points.txt
pyrockoeost-2024.21.dist-info/top_level.txt
pyrockoeost-2024.21.dist-info/RECORD
