Metadata-Version: 2.1
Name: pyrockoeost
Version: 2024.21
Summary: A versatile seismology toolkit for Python.
Author-email: The pyrockoeost Developers <pyrocko@gmail.com>
Maintainer-email: Pyrocko EOST <pyrocko@gmail.com>
License: GPLv3
Project-URL: homepage, https://pyrocko.org
Project-URL: documentation, https://pyrocko.org/docs
Project-URL: repository, https://git.pyrocko.org
Project-URL: changelog, https://git.pyrocko.org/pyrocko/pyrocko/src/branch/master/CHANGELOG.md
Keywords: seismology,waveform analysis,earthquake modelling,geophysics,geophysical inversion
Classifier: License :: OSI Approved :: GNU General Public License v3 (GPLv3)
Classifier: Development Status :: 5 - Production/Stable
Classifier: Intended Audience :: Science/Research
Classifier: Programming Language :: Python :: 2.7
Classifier: Programming Language :: Python :: 3
Classifier: Programming Language :: C
Classifier: Programming Language :: Python :: Implementation :: CPython
Classifier: Operating System :: POSIX
Classifier: Operating System :: MacOS
Classifier: Topic :: Scientific/Engineering
Classifier: Topic :: Scientific/Engineering :: Physics
Classifier: Topic :: Scientific/Engineering :: Visualization
Classifier: Topic :: Scientific/Engineering :: Information Analysis
Classifier: Topic :: Software Development :: Libraries :: Application Frameworks
Requires-Python: >=3.7
License-File: LICENSE.md
License-File: AUTHORS.md
Requires-Dist: numpy ==1.26.4
Requires-Dist: scipy >=1.0
Requires-Dist: pyyaml ==6.0.1
Requires-Dist: matplotlib <3.9
Requires-Dist: requests ==2.32.3
Requires-Dist: PyQt5 ==5.15.10
Requires-Dist: PyQtWebEngine ==5.15.6
Requires-Dist: vtk ==9.3.1
